ramp_mcp/__init__.py
ramp_mcp/__main__.py
ramp_mcp/client.py
ramp_mcp/constants.py
ramp_mcp/memory_db.py
ramp_mcp/tools.py
ramp_mcp/types.py
ramp_mcp/utils.py
ramp_mcp-0.0.1.dist-info/licenses/LICENSE.txt
ramp_mcp-0.0.1.dist-info/METADATA
ramp_mcp-0.0.1.dist-info/WHEEL
ramp_mcp-0.0.1.dist-info/entry_points.txt
ramp_mcp-0.0.1.dist-info/top_level.txt
ramp_mcp-0.0.1.dist-info/RECORD
