Metadata-Version: 2.4
Name: ramp-mcp
Version: 0.0.1
Summary: Ramp MCP Demo
Requires-Python: ~=3.10
License-File: LICENSE.txt
Requires-Dist: httpx>=0.28.1
Requires-Dist: mcp[cli]>=1.3.0
Requires-Dist: uuid>=1.30.0
Requires-Dist: iso4217>=1.12.20240625
Requires-Dist: flatten-json>=0.1.14
Dynamic: license-file
